ase_gpatom-1.0.0.dist-info/licenses/LICENSE
gpatom/__init__.py
gpatom/acquisition.py
gpatom/aidmep.py
gpatom/aidmin.py
gpatom/aidneb.py
gpatom/aidts.py
gpatom/gpmin.py
gpatom/io.py
gpatom/lgpmin.py
gpatom/beacon/__init__.py
gpatom/beacon/beacon.py
gpatom/beacon/inout.py
gpatom/beacon/str_gen.py
gpatom/fractional_beacon/hsicebeacon.py
gpatom/fractional_beacon/icebeacon.py
gpatom/fractional_beacon/str_gen.py
gpatom/fractional_beacon/unitcell_handler.py
gpatom/fractional_beacon/drs/__init__.py
gpatom/fractional_beacon/drs/drs.py
gpatom/fractional_beacon/gpfp/atoms_gp_interface.py
gpatom/fractional_beacon/gpfp/fingerprint.py
gpatom/fractional_beacon/gpfp/gp.py
gpatom/fractional_beacon/gpfp/kernel.py
gpatom/fractional_beacon/gpfp/kerneltypes.py
gpatom/fractional_beacon/gpfp/prior.py
gpatom/gpfp/__init__.py
gpatom/gpfp/atoms_gp_interface.py
gpatom/gpfp/avishart_hpfitter.py
gpatom/gpfp/calculator.py
gpatom/gpfp/database.py
gpatom/gpfp/fingerprint.py
gpatom/gpfp/gp.py
gpatom/gpfp/hpfitter.py
gpatom/gpfp/kernel.py
gpatom/gpfp/kerneltypes.py
gpatom/gpfp/prior.py
gpatom/hyperspatial_beacon/constrainer.py
gpatom/hyperspatial_beacon/hyperspacebeacon.py
gpatom/hyperspatial_beacon/str_gen.py
gpatom/hyperspatial_beacon/gpfp/fingerprint.py
gpatom/hyperspatial_beacon/gpfp/gp.py
gpatom/hyperspatial_beacon/gpfp/kernel.py
gpatom/hyperspatial_beacon/gpfp/prior.py
ase_gpatom-1.0.0.dist-info/METADATA
ase_gpatom-1.0.0.dist-info/WHEEL
ase_gpatom-1.0.0.dist-info/top_level.txt
ase_gpatom-1.0.0.dist-info/RECORD
