Metadata-Version: 2.4
Name: ase-gpatom
Version: 1.0.0
Summary: Atomistic simulation tools based on Gaussian processes
Project-URL: repository, https://gitlab.com/gpatom/ase-gpatom
Requires-Python: >=3.9
License-File: LICENSE
Requires-Dist: ase>=3.25.0
Requires-Dist: scipy>=1.13.1
Requires-Dist: hpfitter>=5.0.0
Dynamic: license-file
